NNeuralNet/NeuralNet.py
NNeuralNet/__init__.py
NNeuralNet-1.0.dist-info/LICENSE
NNeuralNet-1.0.dist-info/METADATA
NNeuralNet-1.0.dist-info/WHEEL
NNeuralNet-1.0.dist-info/top_level.txt
NNeuralNet-1.0.dist-info/RECORD
