Metadata-Version: 2.1
Name: NNeuralNet
Version: 1.0
Summary: Implementation of a Feed Forward Neural Network
Home-page: https://github.com/dl-thops/NeuralNet
Author: Praveen Gorre,Viswanath Tadi
Author-email: cs18b047@smail.iitm.ac.in
License: UNKNOWN
Platform: Windows
Platform: Linux
Platform: Mac OS X
Classifier: Programming Language :: Python :: 3
Classifier: License :: OSI Approved :: MIT License
Classifier: Operating System :: OS Independent
Requires-Python: >=3.6
Requires-Dist: numpy (>=1.18)
Requires-Dist: tqdm (>=4.1.0)
